xpa/ErrorHandler.py
xpa/URLs.py
xpa/XPA.py
xpa/__init__.py
xpa/classes/ACCOUNT_INFO_GAMERTAG.py
xpa/classes/ACCOUNT_INFO_XUID.py
xpa/classes/CLUB_DETAILS.py
xpa/classes/FRIEND_INFO_GAMERTAG.py
xpa/classes/PLAYER_SUMMARY.py
xpa/classes/XUID_PRESENCE.py
xpa/classes/__init__.py
xbox_python_api-0.2.dist-info/LICENSE
xbox_python_api-0.2.dist-info/METADATA
xbox_python_api-0.2.dist-info/WHEEL
xbox_python_api-0.2.dist-info/top_level.txt
xbox_python_api-0.2.dist-info/RECORD
