Metadata-Version: 2.1
Name: xbox-python-api
Version: 0.2
Summary: Xbox API library
Home-page: https://github.com/Rarmash/Xbox-Python-API
Author: Rarmash
License-File: LICENSE
Requires-Dist: requests ==2.32.0
